abdullah_math/__init__.py
abdullah_math/operations.py
abdullah_math-0.1.0.dist-info/licenses/LICENSE
abdullah_math-0.1.0.dist-info/METADATA
abdullah_math-0.1.0.dist-info/WHEEL
abdullah_math-0.1.0.dist-info/top_level.txt
abdullah_math-0.1.0.dist-info/RECORD
