Metadata-Version: 2.4
Name: abdullah_math
Version: 0.1.0
Summary: A simple math operations package
Home-page: https://github.com/yourusername/abdullah_math
Author: Abdullah
Author-email: Abdullah <your.email@example.com>
License: MIT
Project-URL: Homepage, https://github.com/yourusername/abdullah_math
Project-URL: Bug Reports, https://github.com/yourusername/abdullah_math/issues
Project-URL: Source, https://github.com/yourusername/abdullah_math
Keywords: math,arithmetic,calculator
Classifier: Development Status :: 3 - Alpha
Classifier: Intended Audience :: Developers
Classifier: License :: OSI Approved :: MIT License
Classifier: Operating System :: OS Independent
Classifier: Programming Language :: Python :: 3
Classifier: Programming Language :: Python :: 3.7
Classifier: Programming Language :: Python :: 3.8
Classifier: Programming Language :: Python :: 3.9
Classifier: Programming Language :: Python :: 3.10
Classifier: Programming Language :: Python :: 3.11
Requires-Python: >=3.7
License-File: LICENSE
Dynamic: author
Dynamic: home-page
Dynamic: license-file
Dynamic: requires-python
